{
  "annotations": { "list": [] },
  "editable": true,
  "fiscalYearStartMonth": 0,
  "graphTooltip": 0,
  "id": null,
  "links": [],
  "panels": [
    {
      "type": "timeseries",
      "title": "RAG API - Requests/sec",
      "gridPos": { "x": 0, "y": 0, "w": 12, "h": 8 },
      "targets": [
        {
          "expr": "sum(rate(rag_api_requests_total[1m])) by (path)",
          "legendFormat": "{{path}}"
        }
      ]
    },
    {
      "type": "timeseries",
      "title": "RAG API - p95 latency (sec)",
      "gridPos": { "x": 12, "y": 0, "w": 12, "h": 8 },
      "targets": [
        {
          "expr": "histogram_quantile(0.95, sum(rate(rag_api_request_latency_seconds_bucket[5m])) by (le, path))",
          "legendFormat": "p95 {{path}}"
        }
      ]
    },
    {
      "type": "timeseries",
      "title": "Indexer - Messages/sec",
      "gridPos": { "x": 0, "y": 8, "w": 12, "h": 8 },
      "targets": [
        {
          "expr": "sum(rate(rag_indexer_messages_total[1m])) by (result)",
          "legendFormat": "{{result}}"
        }
      ]
    },
    {
      "type": "timeseries",
      "title": "Indexer - DB inserts/sec",
      "gridPos": { "x": 12, "y": 8, "w": 12, "h": 8 },
      "targets": [
        {
          "expr": "sum(rate(rag_indexer_db_inserts_total[1m])) by (table)",
          "legendFormat": "{{table}}"
        }
      ]
    },
    {
      "type": "timeseries",
      "title": "Postgres - Connections",
      "gridPos": { "x": 0, "y": 16, "w": 12, "h": 8 },
      "targets": [
        {
          "expr": "pg_stat_activity_count",
          "legendFormat": "connections"
        }
      ]
    },
    {
      "type": "timeseries",
      "title": "Containers - CPU usage (cAdvisor)",
      "gridPos": { "x": 12, "y": 16, "w": 12, "h": 8 },
      "targets": [
        {
          "expr": "sum(rate(container_cpu_usage_seconds_total{container!=\"\"}[1m])) by (container)",
          "legendFormat": "{{container}}"
        }
      ]
    }
  ],
  "schemaVersion": 39,
  "style": "dark",
  "tags": ["wikimedia", "rag"],
  "templating": { "list": [] },
  "time": { "from": "now-30m", "to": "now" },
  "timepicker": {},
  "timezone": "utc",
  "title": "Wikimedia RAG - Flow Overview",
  "uid": "wikimedia-rag-flow",
  "version": 1
}
